{
    "metadata": {
        "company_name": "Avr.lux 673 lux - Uniformity O.41 mostafaattalla122@gmail.com 1 NESSTRA Luminaire list 54OO.O W 145.O lm/W pcs. Manufacturer Article No. Article name P Φ Luminous efficacy 36 Philips BY698P LED265CW G2 WB 15O.O W 2175O lm 145.O lm/W 2 NESSTRA Building 1 · Storey 1 · Room 1 Luminaire layout plan 3 NESSTRA Building 1 · Storey 1 · Room 1 Luminaire layout plan Manufacturer Philips P 15O.O W Article name BY698P LED265CW ΦLuminaire 2175O lm G2 WB Fitting 1x LED 36 x Philips BY698P LED265CW G2 WB Type Field Arrangement X Y Mounting Luminaire height 1st luminaire (X/Y/Z) 4.OOO m / 4.OO2 m / 7.OOO m 4.OOO m 36.OO2 m 7.OOO m 1 X-direction 4 pcs., Centre - 8.OOO m 36.OO2 m 7.OOO m 2 centre, Distances not equal 12.OOO m 36.OO2 m 7.OOO m 3 Y-direction 9 pcs., Centre - 16.OOO m 36.OO2 m 7.OOO m 4 centre, Distances not equal 4.OOO m 32.OO2 m 7.OOO m 5 Arrangement A1 8.OOO m 32.OO2 m 7.OOO m 6 12.OOO m 32.OO2 m 7.OOO m 7 16.OOO m 32.OO2 m 7.OOO m 8 4.OOO m 28.OO2 m 7.OOO m 9 8.OOO m 28.OO2 m 7.OOO m 12.OOO m 28.OO2 m 7.OOO m 16.OOO m 28.OO2 m 7.OOO m 4.OOO m 24.OO2 m 7.OOO m 4 NESSTRA Building 1 · Storey 1 · Room 1 Luminaire layout plan X Y Mounting Luminaire height 8.OOO m 24.OO2 m 7.OOO m 14 12.OOO m 24.OO2 m 7.OOO m 15 16.OOO m 24.OO2 m 7.OOO m 16 4.OOO m 2O.OO2 m 7.OOO m 17 8.OOO m 2O.OO2 m 7.OOO m 18 12.OOO m 2O.OO2 m 7.OOO m 19 16.OOO m 2O.OO2 m 7.OOO m 2O 4.OOO m 16.OO2 m 7.OOO m 21 8.OOO m 16.OO2 m 7.OOO m 22 12.OOO m 16.OO2 m 7.OOO m 23 16.OOO m 16.OO2 m 7.OOO m 24 4.OOO m 12.OO2 m 7.OOO m 25 8.OOO m 12.OO2 m 7.OOO m 26 12.OOO m 12.OO2 m 7.OOO m 27 16.OOO m 12.OO2 m 7.OOO m 28 4.OOO m 8.OO2 m 7.OOO m 29 8.OOO m 8.OO2 m 7.OOO m 3O 12.OOO m 8.OO2 m 7.OOO m 31 16.OOO m 8.OO2 m 7.OOO m 32 4.OOO m 4.OO2 m 7.OOO m 33 8.OOO m 4.OO2 m 7.OOO m 34 12.OOO m 4.OO2 m 7.OOO m 35 16.OOO m 4.OO2 m 7.OOO m 36 5 NESSTRA Building 1 · Storey 1 · Room 1 (Light scene 1) the factory Properties Ē Emin Emax Uo (g1) g2 Index the factory 673 lx 277 lx 949 lx O.41 O.29 CG1 Perpendicular illuminance Height: O.OOO m Utilisation profile: Health care premises - Operating areas (5.46.1 Pre-op and recovery rooms) 6 NESSTRA Building 1 · Storey 1 · Room 1 (Light scene 1) working place Properties Ē Emin Emax Uo (g1) g2 Index working place 721 lx 356 lx 954 lx O.49 O.37 CG2 Perpendicular illuminance Height: O.OOO m Utilisation profile: Health care premises - Operating areas (5.46.1 Pre-op and recovery rooms) 7",
        "project_name": "for nesstra factory with HighBay light Technical Engineer Eng.Mostafa Emad - No. of fixutr are 36 x HighBay 15O watt - Height of fixtures is 7 m Short Cicuit Company - Avr.lux 673 lux - Uniformity O.41 mostafaattalla122@gmail.com 1 NESSTRA Luminaire list 54OO.O W 145.O lm/W pcs. Manufacturer Article No. Article name P Φ Luminous efficacy 36 Philips BY698P LED265CW G2 WB 15O.O W 2175O lm 145.O lm/W 2 NESSTRA Building 1 · Storey 1 · Room 1 Luminaire layout plan 3 NESSTRA Building 1 · Storey 1 · Room 1 Luminaire layout plan Manufacturer Philips P 15O.O W Article name BY698P LED265CW ΦLuminaire 2175O lm G2 WB Fitting 1x LED 36 x Philips BY698P LED265CW G2 WB Type Field Arrangement X Y Mounting Luminaire height 1st luminaire (X/Y/Z) 4.OOO m / 4.OO2 m / 7.OOO m 4.OOO m 36.OO2 m 7.OOO m 1 X-direction 4 pcs., Centre - 8.OOO m 36.OO2 m 7.OOO m 2 centre, Distances not equal 12.OOO m 36.OO2 m 7.OOO m 3 Y-direction 9 pcs., Centre - 16.OOO m 36.OO2 m 7.OOO m 4 centre, Distances not equal 4.OOO m 32.OO2 m 7.OOO m 5 Arrangement A1 8.OOO m 32.OO2 m 7.OOO m 6 12.OOO m 32.OO2 m 7.OOO m 7 16.OOO m 32.OO2 m 7.OOO m 8 4.OOO m 28.OO2 m 7.OOO m 9 8.OOO m 28.OO2 m 7.OOO m 12.OOO m 28.OO2 m 7.OOO m 16.OOO m 28.OO2 m 7.OOO m 4.OOO m 24.OO2 m 7.OOO m 4 NESSTRA Building 1 · Storey 1 · Room 1 Luminaire layout plan X Y Mounting Luminaire height 8.OOO m 24.OO2 m 7.OOO m 14 12.OOO m 24.OO2 m 7.OOO m 15 16.OOO m 24.OO2 m 7.OOO m 16 4.OOO m 2O.OO2 m 7.OOO m 17 8.OOO m 2O.OO2 m 7.OOO m 18 12.OOO m 2O.OO2 m 7.OOO m 19 16.OOO m 2O.OO2 m 7.OOO m 2O 4.OOO m 16.OO2 m 7.OOO m 21 8.OOO m 16.OO2 m 7.OOO m 22 12.OOO m 16.OO2 m 7.OOO m 23 16.OOO m 16.OO2 m 7.OOO m 24 4.OOO m 12.OO2 m 7.OOO m 25 8.OOO m 12.OO2 m 7.OOO m 26 12.OOO m 12.OO2 m 7.OOO m 27 16.OOO m 12.OO2 m 7.OOO m 28 4.OOO m 8.OO2 m 7.OOO m 29 8.OOO m 8.OO2 m 7.OOO m 3O 12.OOO m 8.OO2 m 7.OOO m 31 16.OOO m 8.OO2 m 7.OOO m 32 4.OOO m 4.OO2 m 7.OOO m 33 8.OOO m 4.OO2 m 7.OOO m 34 12.OOO m 4.OO2 m 7.OOO m 35 16.OOO m 4.OO2 m 7.OOO m 36 5 NESSTRA Building 1 · Storey 1 · Room 1 (Light scene 1) the factory Properties Ē Emin Emax Uo (g1) g2 Index the factory 673 lx 277 lx 949 lx O.41 O.29 CG1 Perpendicular illuminance Height: O.OOO m Utilisation profile: Health care premises - Operating areas (5.46.1 Pre-op and recovery rooms) 6 NESSTRA Building 1 · Storey 1 · Room 1 (Light scene 1) working place Properties Ē Emin Emax Uo (g1) g2 Index working place 721 lx 356 lx 954 lx O.49 O.37 CG2 Perpendicular illuminance Height: O.OOO m Utilisation profile: Health care premises - Operating areas (5.46.1 Pre-op and recovery rooms) 7",
        "engineer": "ineer Eng",
        "email": "mostafaattalla122@gmail.com",
        "report_title": null
    },
    "lighting_setup": {
        "number_of_fixtures": 1,
        "fixture_type": "Unknown",
        "mounting_height_m": 0.0,
        "average_lux": 0,
        "uniformity": 0.0,
        "total_power_w": 0.0,
        "luminous_efficacy_lm_per_w": 0.0
    },
    "luminaires": [
        {
            "manufacturer": "Article",
            "article_no": "Unknown",
            "power_w": 2.0,
            "luminous_flux_lm": 0,
            "efficacy_lm_per_w": 0.0,
            "quantity": 1
        }
    ],
    "rooms": [
        {
            "name": "Building 1 · Storey 1 · Room 1",
            "arrangement": "A1",
            "layout": []
        },
        {
            "name": "Building 1 · Storey 1 · Room 1",
            "arrangement": "A1",
            "layout": []
        },
        {
            "name": "Building 1 · Storey 1 · Room 1",
            "arrangement": "A1",
            "layout": []
        },
        {
            "name": "Building 1 · Storey 1 · Room 1",
            "arrangement": "A1",
            "layout": []
        },
        {
            "name": "Building 1 · Storey 1 · Room 1",
            "arrangement": "A1",
            "layout": []
        },
        {
            "name": "Room 1",
            "arrangement": "A1",
            "layout": []
        },
        {
            "name": "Room 1",
            "arrangement": "A1",
            "layout": []
        },
        {
            "name": "Room 1",
            "arrangement": "A1",
            "layout": []
        },
        {
            "name": "Room 1",
            "arrangement": "A1",
            "layout": []
        },
        {
            "name": "Room 1",
            "arrangement": "A1",
            "layout": []
        }
    ],
    "scenes": [
        {
            "scene_name": "the factory",
            "average_lux": 0,
            "min_lux": 0,
            "max_lux": 0,
            "uniformity": 0.0,
            "utilisation_profile": "Health care premises - Operating areas (5.46.1 Pre-op and recovery rooms)"
        },
        {
            "scene_name": "the factory",
            "average_lux": 0,
            "min_lux": 0,
            "max_lux": 0,
            "uniformity": 0.0,
            "utilisation_profile": "Health care premises - Operating areas (5.46.1 Pre-op and recovery rooms)"
        },
        {
            "scene_name": "working place",
            "average_lux": 0,
            "min_lux": 0,
            "max_lux": 0,
            "uniformity": 0.0,
            "utilisation_profile": "Health care premises - Operating areas (5.46.1 Pre-op and recovery rooms)"
        },
        {
            "scene_name": "working place",
            "average_lux": 0,
            "min_lux": 0,
            "max_lux": 0,
            "uniformity": 0.0,
            "utilisation_profile": "Health care premises - Operating areas (5.46.1 Pre-op and recovery rooms)"
        }
    ]
}